<?xml version="1.0" encoding="utf-8" ?>

 
<Defs>

    <TraitDef>
        <defName>Gifted</defName>
        <commonality>0.001</commonality>
        <degreeDatas>
            <li>
                <label>magically gifted</label>
                <description>NAME has a magical gift. HE can harness this gift to become a mage by studying the mysterious secrets within an arcane script.</description>
						<degree>2</degree>
                <statOffsets>
                    <MoveSpeed>.10</MoveSpeed>
                    <MedicalTendSpeed>.1</MedicalTendSpeed>
                    <ImmunityGainSpeed>.1</ImmunityGainSpeed>
					<PsychicSensitivity>0.20</PsychicSensitivity>
					<GlobalLearningFactor>.10</GlobalLearningFactor>
                </statOffsets>
            </li>
        </degreeDatas>
		<conflictingTraits>
		  <li>HeartOfFrost</li>
		  <li>Arcanist</li>
		  <li>StormBorn</li>
		  <li>InnerFire</li>
		  <li>Paladin</li>
		  <li>PhysicalProdigy</li>
		  <li>Summoner</li>
		  <li>Gladiator</li>
		  <li>TM_Sniper</li>
		  <li>Druid</li>
		  <li>Bladedancer</li>
		  <li>Necromancer</li>
		  <li>Priest</li>
		  <li>Ranger</li>
		  <li>Lich</li>
		  <li>TM_Bard</li>
		  <li>Faceless</li>
		</conflictingTraits>
    </TraitDef>
	
	<TraitDef>
		<defName>InnerFire</defName>
		<commonality>0.001</commonality>
		<degreeDatas>	
		  <li>
			<label>Fire mage</label>
			<description>NAME is attuned with the elements of fire.</description>
			<degree>4</degree>
				<statOffsets>
                    <MoveSpeed>.20</MoveSpeed>
					<WorkSpeedGlobal>0.10</WorkSpeedGlobal>
                    <ImmunityGainSpeed>.4</ImmunityGainSpeed>
					<PsychicSensitivity>0.20</PsychicSensitivity>
					<MentalBreakThreshold>0.06</MentalBreakThreshold>
					<ShootingAccuracy>-5</ShootingAccuracy>
					<ComfyTemperatureMax>+15</ComfyTemperatureMax>
					<ComfyTemperatureMin>+7</ComfyTemperatureMin>
                </statOffsets>
		  </li>
		</degreeDatas>
		<conflictingTraits>
		  <li>HeartOfFrost</li>
		  <li>Arcanist</li>
		  <li>StormBorn</li>
		  <li>Summoner</li>
			<li>Gifted</li>
			<li>Paladin</li>
			<li>PhysicalProdigy</li>
		  <li>Gladiator</li>
		  <li>TM_Sniper</li>
		  <li>Druid</li>
		  <li>Bladedancer</li>
		  <li>Necromancer</li>
		  <li>Priest</li>
		  <li>Ranger</li>
		  <li>Lich</li>
		  <li>TM_Bard</li>
		  <li>Faceless</li>
		</conflictingTraits>	
	</TraitDef> 
	
	<TraitDef>
		<defName>HeartOfFrost</defName>
		<commonality>0.001</commonality>
		<degreeDatas>	
		  <li>
			<label>Ice mage</label>
			<description>NAME is attuned with the elements of water.</description>
			<degree>4</degree>
				<statOffsets>
					<MentalBreakThreshold>-0.10</MentalBreakThreshold>
					<ResearchSpeed>0.20</ResearchSpeed>
					<GlobalLearningFactor>0.10</GlobalLearningFactor>
					<WorkSpeedGlobal>-0.10</WorkSpeedGlobal>					
					<SocialImpact>-0.20</SocialImpact>
					<ComfyTemperatureMax>-7</ComfyTemperatureMax>
					<ComfyTemperatureMin>-15</ComfyTemperatureMin>
                </statOffsets>
		  </li>
		</degreeDatas>
		<conflictingTraits>
		  <li>InnerFire</li>
		  <li>Arcanist</li>
		  <li>StormBorn</li>
		  <li>Summoner</li>
			<li>Gifted</li>
			<li>Paladin</li>
			<li>PhysicalProdigy</li>
		  <li>Gladiator</li>
		  <li>TM_Sniper</li>
		  <li>Druid</li>
		  <li>Bladedancer</li>
		  <li>Necromancer</li>
		  <li>Priest</li>
		  <li>Ranger</li>
		  <li>Lich</li>
		  <li>TM_Bard</li>
		  <li>Faceless</li>
		</conflictingTraits>	
	</TraitDef> 
	
	<TraitDef>
		<defName>StormBorn</defName>
		<commonality>0.001</commonality>
		<degreeDatas>	
		  <li>
			<label>Lightning mage</label>
			<description>NAME is attuned with the elements of lightning.</description>
				<degree>4</degree>
				<statOffsets>
					<MoveSpeed>.20</MoveSpeed>
					<WorkSpeedGlobal>0.10</WorkSpeedGlobal>
					<MeleeDodgeChance>2</MeleeDodgeChance>
					<MiningSpeed>-.4</MiningSpeed>
					<MiningYield>-.2</MiningYield>
                </statOffsets>
		  </li>
		</degreeDatas>
		<conflictingTraits>
		  <li>InnerFire</li>
		  <li>Arcanist</li>
		  <li>HeartOfFrost</li>
		  <li>Summoner</li>
			<li>Gifted</li>
			<li>Paladin</li>
			<li>PhysicalProdigy</li>
		  <li>Gladiator</li>
		  <li>TM_Sniper</li>
		  <li>Druid</li>
		  <li>Bladedancer</li>
		  <li>Necromancer</li>
		  <li>Priest</li>
		  <li>Ranger</li>
		  <li>Lich</li>
		  <li>TM_Bard</li>
		  <li>Faceless</li>
		</conflictingTraits>	
	</TraitDef> 
	
	<TraitDef>
		<defName>Arcanist</defName>
		<commonality>0.001</commonality>
		<degreeDatas>	
		  <li>
			<label>Arcane mage</label>
			<description>NAME is attuned with arcane forces, interacting directly with raw arcane power to move matter and energy at will.</description>
			<degree>4</degree>
			<statOffsets>
				<ResearchSpeed>0.10</ResearchSpeed>
				<GlobalLearningFactor>.20</GlobalLearningFactor>
				<MentalBreakThreshold>0.03</MentalBreakThreshold>
				<SocialImpact>.10</SocialImpact>
				<DiplomacyPower>.10</DiplomacyPower>
				<TradePriceImprovement>.10</TradePriceImprovement>
				<PsychicSensitivity>1.0</PsychicSensitivity>
				<TameAnimalChance>-0.20</TameAnimalChance>
				<TrainAnimalChance>-0.20</TrainAnimalChance>
			</statOffsets>
		  </li>
		</degreeDatas>
		<conflictingTraits>
		  <li>InnerFire</li>
		  <li>HeartOfFrost</li>
		  <li>StormBorn</li>
		  <li>Summoner</li>
			<li>Gifted</li>
			<li>Paladin</li>
			<li>PhysicalProdigy</li>
		  <li>Gladiator</li>
		  <li>TM_Sniper</li>	
			<li>Druid</li>		
			<li>Bladedancer</li>
		<li>Necromancer</li>	
		<li>Priest</li>	
		<li>Ranger</li>	
		<li>Lich</li>	
		<li>TM_Bard</li>
		<li>Faceless</li>		
		</conflictingTraits>	
	</TraitDef>
	
	<TraitDef>
		<defName>Druid</defName>
		<commonality>0.001</commonality>
		<degreeDatas>	
		  <li>
			<label>Druid</label>
			<description>NAME is attuned with the forces of nature.</description>
			<degree>4</degree>
			<statOffsets>
				<ImmunityGainSpeed>0.3</ImmunityGainSpeed>
				<ToxicSensitivity>-0.20</ToxicSensitivity>
				<TameAnimalChance>0.40</TameAnimalChance>
				<TrainAnimalChance>0.20</TrainAnimalChance>
				<SocialImpact>-.10</SocialImpact>
				<DiplomacyPower>-.10</DiplomacyPower>
				<TradePriceImprovement>-.10</TradePriceImprovement>
				<AnimalGatherYield>.20</AnimalGatherYield>
			</statOffsets>
		  </li>
		</degreeDatas>
		<conflictingTraits>
		  <li>InnerFire</li>
		  <li>HeartOfFrost</li>
		  <li>StormBorn</li>
		  <li>Arcanist</li>
		  <li>Summoner</li>
			<li>Gifted</li>
			<li>Paladin</li>
			<li>PhysicalProdigy</li>
		  <li>Gladiator</li>
		  <li>TM_Sniper</li>
		  <li>Bladedancer</li>
		  <li>Necromancer</li>
		  <li>Priest</li>
		  <li>Ranger</li>
		  <li>Lich</li>
		  <li>TM_Bard</li>
		  <li>Faceless</li>
		</conflictingTraits>	
	</TraitDef>
	
	<TraitDef>
		<defName>Paladin</defName>
		<commonality>0.001</commonality>
		<degreeDatas>	
		  <li>
			<label>Paladin</label>
			<description>NAME has been bestowed with divine might and has sworn to uphold justice wherever HE stands.</description>
			<degree>4</degree>
			<statOffsets>
				<MoveSpeed>.10</MoveSpeed>
				<ImmunityGainSpeed>.2</ImmunityGainSpeed>
				<MentalBreakThreshold>-0.02</MentalBreakThreshold>
				<PainShockThreshold>0.10</PainShockThreshold>
				<PsychicSensitivity>-.2</PsychicSensitivity>
				<GlobalLearningFactor>-.15</GlobalLearningFactor>
			</statOffsets>
		  </li>
		</degreeDatas>
		<conflictingTraits>
		  <li>InnerFire</li>
		  <li>HeartOfFrost</li>
		  <li>StormBorn</li>
		  <li>Arcanist</li>
		  <li>Summoner</li>
		  <li>Gifted</li>
		  <li>PhysicalProdigy</li>
		  <li>Gladiator</li>
		  <li>TM_Sniper</li>
		  <li>Druid</li>
		  <li>Bladedancer</li>
		  <li>Necromancer</li>
		  <li>Priest</li>
		  <li>Ranger</li>
		  <li>Lich</li>
		  <li>TM_Bard</li>
		  <li>Faceless</li>
		</conflictingTraits>	
	</TraitDef>

	<TraitDef>
		<defName>Summoner</defName>
		<commonality>0.001</commonality>
		<degreeDatas>	
		  <li>
			<label>Summoner</label>
			<description>NAME is able to summon beings and materialize objects from other planes of existence.</description>
			<degree>4</degree>
			<statOffsets>
				<MoveSpeed>.10</MoveSpeed>
				<ToxicSensitivity>0.10</ToxicSensitivity>
				<ComfyTemperatureMin>-8</ComfyTemperatureMin>
				<ComfyTemperatureMax>+8</ComfyTemperatureMax>
				<RecruitPrisonerChance>.10</RecruitPrisonerChance>
				<SocialImpact>.10</SocialImpact>
			</statOffsets>
		  </li>
		</degreeDatas>
		<conflictingTraits>
		  <li>InnerFire</li>
		  <li>HeartOfFrost</li>
		  <li>StormBorn</li>
		  <li>Arcanist</li>
		  <li>Gifted</li>
		  <li>PhysicalProdigy</li>
		  <li>Paladin</li>
		  <li>Gladiator</li>
		  <li>TM_Sniper</li>
		  <li>Druid</li>
		  <li>Bladedancer</li>
		  <li>Necromancer</li>
		  <li>Priest</li>
		  <li>Ranger</li>
		  <li>Lich</li>
		  <li>TM_Bard</li>
		  <li>Faceless</li>
		</conflictingTraits>	
	</TraitDef> 	
	
	<TraitDef>
		<defName>Necromancer</defName>
		<commonality>0.001</commonality>
		<degreeDatas>	
		  <li>
			<label>Necromancer</label>
			<description>NAME is attuned with the forces of death.</description>
			<degree>4</degree>
			<statOffsets>
				<MoveSpeed>-0.3</MoveSpeed>
				<ComfyTemperatureMin>-20</ComfyTemperatureMin>
				<ImmunityGainSpeed>.4</ImmunityGainSpeed>
				<ToxicSensitivity>-0.40</ToxicSensitivity>
				<MentalBreakThreshold>-0.1</MentalBreakThreshold>
				<GlobalLearningFactor>0.40</GlobalLearningFactor>
				<TradePriceImprovement>-0.5</TradePriceImprovement>
				<RecruitPrisonerChance>-.25</RecruitPrisonerChance>
			</statOffsets>
		  </li>
		</degreeDatas>
		<conflictingTraits>
		  <li>InnerFire</li>
		  <li>HeartOfFrost</li>
		  <li>StormBorn</li>
		  <li>Arcanist</li>
		  <li>Summoner</li>
			<li>Gifted</li>
			<li>Paladin</li>
			<li>PhysicalProdigy</li>
		  <li>Gladiator</li>
		  <li>TM_Sniper</li>
		  <li>Bladedancer</li>
		  <li>Druid</li>
		  <li>Priest</li>
		  <li>Ranger</li>
		  <li>Lich</li>
		  <li>TM_Bard</li>
		  <li>Faceless</li>
		</conflictingTraits>	
	</TraitDef>
	
	<TraitDef>
		<defName>Lich</defName>
		<commonality>0</commonality>
		<disabledWorkTags> 
			<li>Caring</li>
			<li>Social</li>
			<li>Animals</li>
			<li>Artistic</li>
		    <li>ManualDumb</li>
			<li>ManualSkilled</li>
			<li>Firefighting</li>
		</disabledWorkTags>
		<degreeDatas>	
		  <li>
			<label>Lich</label>
			<description>NAME has transformed into a lich, forsaking life in exchange for an power and an immortal existence, choosing to employ undead for menial tasks.</description>
			<degree>4</degree>
			<statOffsets>
				<MoveSpeed>-2</MoveSpeed>
				<ComfyTemperatureMin>-40</ComfyTemperatureMin>
				<ImmunityGainSpeed>1</ImmunityGainSpeed>
				<ToxicSensitivity>-1</ToxicSensitivity>
				<MentalBreakThreshold>-0.2</MentalBreakThreshold>
				<GlobalLearningFactor>0.6</GlobalLearningFactor>
				<TradePriceImprovement>-0.5</TradePriceImprovement>
				<RecruitPrisonerChance>-.5</RecruitPrisonerChance>
			</statOffsets>
			<skillGains>
			  <li>
				<key>Intellectual</key>
				<value>2</value>
			  </li>
			</skillGains>
			<theOnlyAllowedMentalBreaks>
				<li>SadisticRage</li>
				<li>CorpseObsession</li>
				<li>MurderousRage</li>
				<li>Slaughterer</li>
			</theOnlyAllowedMentalBreaks>
			<disallowedMentalStates>
				<li>WanderConfused</li>
				<li>PanicFlee</li>
				<li>Manhunter</li>
				<li>ManhunterPermanent</li>
			</disallowedMentalStates>
		  </li>
		</degreeDatas>
		<conflictingTraits>
		  <li>InnerFire</li>
		  <li>HeartOfFrost</li>
		  <li>StormBorn</li>
		  <li>Arcanist</li>
		  <li>Summoner</li>
			<li>Gifted</li>
			<li>Paladin</li>
			<li>PhysicalProdigy</li>
		  <li>Gladiator</li>
		  <li>TM_Sniper</li>
		  <li>Bladedancer</li>
		  <li>Druid</li>
		  <li>Priest</li>
		  <li>Ranger</li>
		  <li>Necromancer</li>
		  <li>TM_Bard</li>
		  <li>Faceless</li>
		</conflictingTraits>	
	</TraitDef>
	
	<TraitDef>
		<defName>Priest</defName>
		<commonality>0.001</commonality>
		<disabledWorkTags>
		  <li>Violent</li>
		</disabledWorkTags>
		<degreeDatas>	
		  <li>
			<label>Priest</label>
			<description>NAME is attuned with the forces of life and healing and has taken a vow against harming others.</description>
			<degree>4</degree>
			<statOffsets>
				<MoveSpeed>0.15</MoveSpeed>
				<ImmunityGainSpeed>0.3</ImmunityGainSpeed>
				<MedicalSurgerySuccessChance>0.25</MedicalSurgerySuccessChance>
				<MedicalTendQuality>0.25</MedicalTendQuality>
				<MedicalOperationSpeed>0.25</MedicalOperationSpeed>
				<MedicalTendSpeed>0.25</MedicalTendSpeed>
				<PainShockThreshold>-.10</PainShockThreshold>
			</statOffsets>
			<skillGains>
				<li>
					<key>Medicine</key>
					<value>2</value>
				</li>
			</skillGains>
		  </li>
		</degreeDatas>
		<conflictingTraits>
		  <li>InnerFire</li>
		  <li>HeartOfFrost</li>
		  <li>StormBorn</li>
		  <li>Arcanist</li>
		  <li>Summoner</li>
			<li>Gifted</li>
			<li>Paladin</li>
			<li>PhysicalProdigy</li>
		  <li>Gladiator</li>
		  <li>TM_Sniper</li>
		  <li>Bladedancer</li>
		  <li>Druid</li>
		  <li>Necromancer</li>
		  <li>Psychopath</li>
		  <li>Bloodlust</li>
		  <li>Ranger</li>
		  <li>Lich</li>
		  <li>TM_Bard</li>
		  <li>Faceless</li>
		</conflictingTraits>	
	</TraitDef>
	
	<TraitDef>
		<defName>Undead</defName>
		<disabledWorkTags> 
			<li>Caring</li>
			<li>Social</li>
			<li>Animals</li>
			<li>Artistic</li>
			<li>Intellectual</li>
		</disabledWorkTags>
		<degreeDatas>	
		  <li>
			<label>Undead</label>
			<description>NAME has been reanimated as an undead.</description>
			<degree>0</degree>
			<statOffsets>
				<MoveSpeed>-2</MoveSpeed>
				<ComfyTemperatureMin>-200</ComfyTemperatureMin>
				<ComfyTemperatureMax>50</ComfyTemperatureMax>
				<ToxicSensitivity>-1</ToxicSensitivity>
				<ImmunityGainSpeed>49</ImmunityGainSpeed>
				<PainShockThreshold>0.90</PainShockThreshold>
				<DiplomacyPower>-0.5</DiplomacyPower>
				<WorkSpeedGlobal>-0.40</WorkSpeedGlobal>
			</statOffsets>
		  </li>
		</degreeDatas>	
	</TraitDef>

	<TraitDef>
		<defName>TM_Bard</defName>
		<commonality>0.001</commonality>	
		<disabledWorkTags>
		  <li>ManualDumb</li>
		</disabledWorkTags>		
		<degreeDatas>	
		  <li>
			<label>Entertainer</label>
			<commonality>0.1</commonality>
			<description>NAME is a natural entertainer, able to lighten the mood and lift the spirits of everyone around HIM.</description>
			<degree>0</degree>
				<statOffsets>
					<RecruitPrisonerChance>0.10</RecruitPrisonerChance>
					<SocialImpact>0.10</SocialImpact>
					<DiplomacyPower>0.20</DiplomacyPower>
					<TradePriceImprovement>0.10</TradePriceImprovement>
                    <PainShockThreshold>-0.10</PainShockThreshold>
					<CarryingCapacity>-0.10</CarryingCapacity>
					<WorkSpeedGlobal>-0.10</WorkSpeedGlobal>					
                </statOffsets>
		  </li>
		  <li>
			<label>Performer</label>
			<commonality>0</commonality>
			<description>NAME is a performer; expanding on natural talent, HE has begun to take an conscious role to improve the mood of other colonists.</description>
			<degree>1</degree>
				<statOffsets>
					<RecruitPrisonerChance>0.15</RecruitPrisonerChance>
					<SocialImpact>0.20</SocialImpact>
					<DiplomacyPower>0.30</DiplomacyPower>
					<TradePriceImprovement>0.15</TradePriceImprovement>
                    <PainShockThreshold>-0.12</PainShockThreshold>
					<CarryingCapacity>-0.15</CarryingCapacity>
					<WorkSpeedGlobal>-0.12</WorkSpeedGlobal>
                </statOffsets>
		  </li>
		  <li>
			<label>Minstrel</label>
			<commonality>0</commonality>
			<description>Everyone loves being around NAME. HE has talent, wit and skill in many forms of entertainment and is able to make a personal connection with almost everyone.</description>
			<degree>2</degree>
				<statOffsets>
					<RecruitPrisonerChance>0.20</RecruitPrisonerChance>
					<SocialImpact>0.30</SocialImpact>
					<DiplomacyPower>0.35</DiplomacyPower>
					<TradePriceImprovement>0.20</TradePriceImprovement>
                    <PainShockThreshold>-0.14</PainShockThreshold>
					<CarryingCapacity>-0.18</CarryingCapacity>
					<WorkSpeedGlobal>-0.14</WorkSpeedGlobal>
                </statOffsets>
		  </li>
		  <li>
			<label>Bard</label>
			<commonality>0</commonality>
			<description>NAME is a master entertainer. Sharp wit, deft hands, and dry humor are HIS weapons and HE is a master of all HIS weapons.</description>
			<degree>3</degree>
				<statOffsets>
					<RecruitPrisonerChance>0.25</RecruitPrisonerChance>
					<SocialImpact>0.35</SocialImpact>
					<DiplomacyPower>0.40</DiplomacyPower>
					<TradePriceImprovement>0.25</TradePriceImprovement>
                    <PainShockThreshold>-0.15</PainShockThreshold>
					<CarryingCapacity>-0.20</CarryingCapacity>
					<WorkSpeedGlobal>-0.15</WorkSpeedGlobal>
                </statOffsets>
		  </li>
		</degreeDatas>
		<conflictingTraits>
		  <li>PhysicalProdigy</li>
		  <li>InnerFire</li>
		  <li>HeartOfFrost</li>
		  <li>Arcanist</li>
		  <li>StormBorn</li>
		  <li>Summoner</li>
		  <li>Gifted</li>
	      <li>Paladin</li>
		  <li>Gladiator</li>
		  <li>Druid</li>
		  <li>TM_Sniper</li>
		  <li>Necromancer</li>
		  <li>Priest</li>
		  <li>Bladedancer</li>
		  <li>Lich</li>
		  <li>Ranger</li>
		  <li>Faceless</li>
		</conflictingTraits>	
	</TraitDef>
	
	<TraitDef>
        <defName>PhysicalProdigy</defName>
        <commonality>0.001</commonality>
        <degreeDatas>
            <li>
                <label>physically adept</label>
                <description>NAME is physically adept and has potential to learn special combat forms.</description>
						<degree>2</degree>
                <statOffsets>
                    <MoveSpeed>.20</MoveSpeed>
					<WorkSpeedGlobal>0.20</WorkSpeedGlobal>
                    <ImmunityGainSpeed>.2</ImmunityGainSpeed>
					<PsychicSensitivity>-0.4</PsychicSensitivity>
					<GlobalLearningFactor>-.20</GlobalLearningFactor>
                </statOffsets>
            </li>
        </degreeDatas>
		<conflictingTraits>
		  <li>Gladiator</li>
		  <li>InnerFire</li>
		  <li>HeartOfFrost</li>
		  <li>Summoner</li>
		  <li>Arcanist</li>
		  <li>StormBorn</li>
		  <li>Gifted</li>
	      <li>Paladin</li>
		  <li>TM_Sniper</li>
		  <li>Druid</li>
		  <li>Bladedancer</li>
		  <li>Necromancer</li>
		  <li>Priest</li>
		  <li>Ranger</li>
		  <li>Lich</li>
		  <li>TM_Bard</li>
		  <li>Faceless</li>
		</conflictingTraits>
    </TraitDef>
	
	<TraitDef>
		<defName>Gladiator</defName>
		<commonality>0.001</commonality>
		<degreeDatas>	
		  <li>
			<label>Gladiator</label>
			<description>NAME has learned how to train the Gladiator combat style.</description>
			<degree>4</degree>
				<statOffsets>
                    <MoveSpeed>.20</MoveSpeed>
					<WorkSpeedGlobal>0.20</WorkSpeedGlobal>
                    <ImmunityGainSpeed>.4</ImmunityGainSpeed>
					<PsychicSensitivity>-0.6</PsychicSensitivity>
					<MentalBreakThreshold>0.05</MentalBreakThreshold>
					<GlobalLearningFactor>-.20</GlobalLearningFactor>
					<MeleeDodgeChance>4</MeleeDodgeChance>
					<MiningSpeed>0.2</MiningSpeed>
					<MiningYield>0.2</MiningYield>
					<PlantWorkSpeed>-.2</PlantWorkSpeed>
					<PlantHarvestYield>-.2</PlantHarvestYield>
					<ResearchSpeed>-.2</ResearchSpeed>
                </statOffsets>
		  </li>
		</degreeDatas>
		<conflictingTraits>
		  <li>PhysicalProdigy</li>
		  <li>InnerFire</li>
		  <li>HeartOfFrost</li>
		  <li>Arcanist</li>
		  <li>StormBorn</li>
		  <li>Summoner</li>
		  <li>Gifted</li>
	      <li>Paladin</li>
		  <li>TM_Sniper</li>
		  <li>Druid</li>
		  <li>Bladedancer</li>
		  <li>Necromancer</li>
		  <li>Priest</li>
		  <li>Ranger</li>
		  <li>Lich</li>
		  <li>TM_Bard</li>
		  <li>Faceless</li>
		</conflictingTraits>	
	</TraitDef>
	
	<TraitDef>
		<defName>Ranger</defName>
		<commonality>0.001</commonality>		
		<degreeDatas>	
		  <li>
			<label>Woodsman</label>
			<commonality>0.1</commonality>
			<description>NAME is a trained woodsman; preferring the silence and lethality of a bow and armed with field-craft and cunning, HE is prepared to defend HIS land from invaders.</description>
			<degree>0</degree>
				<statOffsets>
					<MoveSpeed>.15</MoveSpeed>
					<ImmunityGainSpeed>0.20</ImmunityGainSpeed>
					<ComfyTemperatureMax>+10</ComfyTemperatureMax>
					<ComfyTemperatureMin>-10</ComfyTemperatureMin>
                    <AimingDelayFactor>-0.15</AimingDelayFactor>
					<ToxicSensitivity>-.10</ToxicSensitivity>
					<ButcheryFleshSpeed>0.05</ButcheryFleshSpeed>
					<SmeltingSpeed>-0.10</SmeltingSpeed>
					<ConstructionSpeed>-.05</ConstructionSpeed>
					<TameAnimalChance>.05</TameAnimalChance>
					<TrainAnimalChance>.05</TrainAnimalChance>
                </statOffsets>
		  </li>
		  <li>
			<label>Hunter</label>
			<commonality>0</commonality>
			<description>NAME is a hunter; HE employs field-craft, cunning, and skill with a bow to defend HIS land from invaders.</description>
			<degree>1</degree>
				<statOffsets>
					<MoveSpeed>.2</MoveSpeed>
					<ImmunityGainSpeed>0.3</ImmunityGainSpeed>
					<ComfyTemperatureMax>+15</ComfyTemperatureMax>
					<ComfyTemperatureMin>-15</ComfyTemperatureMin>
                    <AimingDelayFactor>-0.20</AimingDelayFactor>
					<ToxicSensitivity>-.15</ToxicSensitivity>
					<ButcheryFleshSpeed>0.10</ButcheryFleshSpeed>
					<SmeltingSpeed>-0.15</SmeltingSpeed>
					<ConstructionSpeed>-.10</ConstructionSpeed>
					<TameAnimalChance>.08</TameAnimalChance>
					<TrainAnimalChance>.08</TrainAnimalChance>
                </statOffsets>
		  </li>
		  <li>
			<label>Scout</label>
			<commonality>0</commonality>
			<description>NAME is a scout; comfortable in the wilds, and relied upon to be the eyes and ears of a colony.  HE employs expertise in field-craft, cunning, and the bow to defend HIS land from invaders.</description>
			<degree>2</degree>
				<statOffsets>
					<MoveSpeed>.25</MoveSpeed>
					<ImmunityGainSpeed>0.4</ImmunityGainSpeed>
					<ComfyTemperatureMax>+20</ComfyTemperatureMax>
					<ComfyTemperatureMin>-20</ComfyTemperatureMin>
                    <AimingDelayFactor>-0.30</AimingDelayFactor>
					<ToxicSensitivity>-.20</ToxicSensitivity>
					<ButcheryFleshSpeed>0.15</ButcheryFleshSpeed>
					<SmeltingSpeed>-0.18</SmeltingSpeed>
					<ConstructionSpeed>-.13</ConstructionSpeed>
					<TameAnimalChance>.10</TameAnimalChance>
					<TrainAnimalChance>.10</TrainAnimalChance>
                </statOffsets>
		  </li>
		  <li>
			<label>Ranger</label>
			<commonality>0</commonality>
			<description>NAME is a ranger; master of the wilds.  HE is a master of HIS craft and defender of HIS land.</description>
			<degree>3</degree>
				<statOffsets>
					<MoveSpeed>.3</MoveSpeed>
					<ImmunityGainSpeed>0.5</ImmunityGainSpeed>
					<ComfyTemperatureMax>+25</ComfyTemperatureMax>
					<ComfyTemperatureMin>-25</ComfyTemperatureMin>
                    <AimingDelayFactor>-0.40</AimingDelayFactor>
					<ToxicSensitivity>-.25</ToxicSensitivity>
					<ButcheryFleshSpeed>0.20</ButcheryFleshSpeed>
					<SmeltingSpeed>-0.20</SmeltingSpeed>
					<ConstructionSpeed>-.15</ConstructionSpeed>
					<TameAnimalChance>.12</TameAnimalChance>
					<TrainAnimalChance>.12</TrainAnimalChance>
					
                </statOffsets>
		  </li>
		</degreeDatas>
		<conflictingTraits>
		  <li>PhysicalProdigy</li>
		  <li>InnerFire</li>
		  <li>HeartOfFrost</li>
		  <li>Arcanist</li>
		  <li>StormBorn</li>
		  <li>Summoner</li>
		  <li>Gifted</li>
	      <li>Paladin</li>
		  <li>Gladiator</li>
		  <li>Druid</li>
		  <li>TM_Sniper</li>
		  <li>Necromancer</li>
		  <li>Priest</li>
		  <li>Bladedancer</li>
		  <li>Lich</li>
		  <li>TM_Bard</li>
		  <li>Faceless</li>
		</conflictingTraits>	
	</TraitDef>
	
	<TraitDef>
		<defName>TM_Sniper</defName>
		<commonality>0.001</commonality>
		<degreeDatas>	
		  <li>
			<label>Sharpshooter</label>
			<commonality>0.1</commonality>
			<description>NAME has trained to become a sniper, skilled in the economy and accuracy of long range, small arms combat. Training to become a sniper has caused some colonists to be uncomfortable around HIM, not that HE cares.</description>
			<degree>0</degree>
				<statOffsets>
					<MoveSpeed>.10</MoveSpeed>
                    <AimingDelayFactor>-0.10</AimingDelayFactor>
					<ShootingAccuracy>3</ShootingAccuracy>
					<ResearchSpeed>-0.10</ResearchSpeed>
					<WorkSpeedGlobal>-.10</WorkSpeedGlobal>
					<TameAnimalChance>-.10</TameAnimalChance>
					<TrainAnimalChance>-.10</TrainAnimalChance>
                </statOffsets>
		  </li>
		  <li>
			<label>Sniper</label>
			<commonality>0.0</commonality>
			<description>NAME has trained to become a sniper, skilled in the economy and accuracy of long range, small arms combat. Becoming a sniper has caused HIM to become distanced from other colonists and somewhat unapproachable, not that HE cares.</description>
			<degree>1</degree>
				<statOffsets>
					<MoveSpeed>.15</MoveSpeed>
                    <AimingDelayFactor>-0.15</AimingDelayFactor>
					<ShootingAccuracy>7</ShootingAccuracy>
					<ResearchSpeed>-0.13</ResearchSpeed>
					<WorkSpeedGlobal>-.13</WorkSpeedGlobal>
					<TameAnimalChance>-.13</TameAnimalChance>
					<TrainAnimalChance>-.13</TrainAnimalChance>
                </statOffsets>
		  </li>
		  <li>
			<label>Master Sniper</label>
			<commonality>0.0</commonality>
			<description>NAME is a master sniper, skilled in the economy and accuracy of long range, small arms combat. Being a sniper has made HIM avoid other colonists, not that they care.</description>
			<degree>2</degree>
				<statOffsets>
					<MoveSpeed>.20</MoveSpeed>
                    <AimingDelayFactor>-0.22</AimingDelayFactor>
					<ShootingAccuracy>11</ShootingAccuracy>
					<ResearchSpeed>-0.15</ResearchSpeed>
					<WorkSpeedGlobal>-.15</WorkSpeedGlobal>
					<TameAnimalChance>-.15</TameAnimalChance>
					<TrainAnimalChance>-.15</TrainAnimalChance>
                </statOffsets>
		  </li>
		  <li>
			<label>Legendary Sniper</label>
			<commonality>0.0</commonality>
			<description>NAME is a legendary sniper, skilled in the economy and accuracy of long range, small arms combat.  Other colonists avoid eye contact and whisper in corners about how dangerous HE is.  HE quite likes it when they do.</description>
			<degree>3</degree>
				<statOffsets>
					<MoveSpeed>.25</MoveSpeed>
                    <AimingDelayFactor>-0.30</AimingDelayFactor>
					<ShootingAccuracy>15</ShootingAccuracy>
					<ResearchSpeed>-0.16</ResearchSpeed>
					<WorkSpeedGlobal>-.16</WorkSpeedGlobal>
					<TameAnimalChance>-.16</TameAnimalChance>
					<TrainAnimalChance>-.16</TrainAnimalChance>
                </statOffsets>
		  </li>
		</degreeDatas>
		<conflictingTraits>
		  <li>PhysicalProdigy</li>
		  <li>InnerFire</li>
		  <li>HeartOfFrost</li>
		  <li>Arcanist</li>
		  <li>StormBorn</li>
		  <li>Summoner</li>
		  <li>Gifted</li>
	      <li>Paladin</li>
		  <li>Gladiator</li>
		  <li>Druid</li>
		  <li>Bladedancer</li>
		  <li>Necromancer</li>
		  <li>Priest</li>
		  <li>Ranger</li>
		  <li>Lich</li>
		  <li>TM_Bard</li>
		  <li>Faceless</li>
		</conflictingTraits>	
	</TraitDef>
	
	<TraitDef>
		<defName>Bladedancer</defName>
		<commonality>0.001</commonality>		
		<degreeDatas>	
		  <li>
			<label>Bladesman</label>
			<commonality>0.1</commonality>
			<description>NAME is training to become a master of the blade and excels at fighting in melee combat.</description>
			<degree>0</degree>
				<statOffsets>
					<MoveSpeed>.15</MoveSpeed>
                    <MentalBreakThreshold>-0.03</MentalBreakThreshold>
					<MeleeHitChance>3</MeleeHitChance>
					<ShootingAccuracy>-20</ShootingAccuracy>
					<WorkSpeedGlobal>-.10</WorkSpeedGlobal>
                </statOffsets>
		  </li>
		  <li>
			<label>Blademaster</label>
			<commonality>0</commonality>
			<description>NAME has trained to become a sword master, dangerously skilled in melee combat.</description>
			<degree>1</degree>
				<statOffsets>
					<MoveSpeed>.20</MoveSpeed>
                    <MentalBreakThreshold>-0.05</MentalBreakThreshold>
					<MeleeHitChance>6</MeleeHitChance>
					<MeleeDodgeChance>5</MeleeDodgeChance>
					<ShootingAccuracy>-25</ShootingAccuracy>
					<WorkSpeedGlobal>-.12</WorkSpeedGlobal>
                </statOffsets>
		  </li>
		  <li>
			<label>Bladedancer</label>
			<commonality>0</commonality>
			<description>NAME is a blade dancer, highly skilled in melee combat.  Watching HECAP fight is like watching a dance, every action precise and flawless as it flows from one form into another.</description>
			<degree>2</degree>
				<statOffsets>
					<MoveSpeed>.30</MoveSpeed>
                    <MentalBreakThreshold>-0.08</MentalBreakThreshold>
					<MeleeHitChance>10</MeleeHitChance>
					<MeleeDodgeChance>10</MeleeDodgeChance>
					<PainShockThreshold>0.05</PainShockThreshold>
					<ShootingAccuracy>-28</ShootingAccuracy>
					<WorkSpeedGlobal>-.14</WorkSpeedGlobal>
                </statOffsets>
		  </li>
		  <li>
			<label>Legendary bladedancer</label>
			<commonality>0</commonality>
			<description>NAME has become a legend, HIS skill in melee combat is is known across the world.  HECAP's skill in combat makes it look as if each movement, each strike, is merely a stitch in a tapestry that depicts HIS victory.</description>
			<degree>3</degree>
				<statOffsets>
					<MoveSpeed>.40</MoveSpeed>
                    <MentalBreakThreshold>-0.10</MentalBreakThreshold>
					<MeleeHitChance>15</MeleeHitChance>
					<MeleeDodgeChance>15</MeleeDodgeChance>
					<PainShockThreshold>0.10</PainShockThreshold>
					<ShootingAccuracy>-30</ShootingAccuracy>
					<WorkSpeedGlobal>-.15</WorkSpeedGlobal>
                </statOffsets>
		  </li>
		</degreeDatas>
		<conflictingTraits>
		  <li>PhysicalProdigy</li>
		  <li>InnerFire</li>
		  <li>HeartOfFrost</li>
		  <li>Arcanist</li>
		  <li>StormBorn</li>
		  <li>Summoner</li>
		  <li>Gifted</li>
	      <li>Paladin</li>
		  <li>Gladiator</li>
		  <li>Druid</li>
		  <li>TM_Sniper</li>
		  <li>Necromancer</li>
		  <li>Priest</li>
		  <li>Ranger</li>
		  <li>Lich</li>
		  <li>TM_Bard</li>
		  <li>Faceless</li>
		</conflictingTraits>	
	</TraitDef>
	
	<TraitDef>
		<defName>Faceless</defName>
		<commonality>0.001</commonality>
		<degreeDatas>	
		  <li>
			<label>Faceless</label>
			<description>NAME is a master of disguise and imitation; able to manipulate and capture the muscle and mental actions of another and release it as their own.</description>
			<degree>4</degree>
				<statOffsets>
                    <MoveSpeed>.15</MoveSpeed>
					<WorkSpeedGlobal>0.1</WorkSpeedGlobal>
                    <ImmunityGainSpeed>.1</ImmunityGainSpeed>
					<PsychicSensitivity>0.5</PsychicSensitivity>
					<MentalBreakThreshold>0.1</MentalBreakThreshold>
					<GlobalLearningFactor>0.20</GlobalLearningFactor>
					<MeleeDodgeChance>4</MeleeDodgeChance>
					<MiningSpeed>-0.1</MiningSpeed>
					<PlantWorkSpeed>-.1</PlantWorkSpeed>
					<ResearchSpeed>-.4</ResearchSpeed>
                </statOffsets>
		  </li>
		</degreeDatas>
		<conflictingTraits>
		  <li>PhysicalProdigy</li>
		  <li>InnerFire</li>
		  <li>HeartOfFrost</li>
		  <li>Arcanist</li>
		  <li>StormBorn</li>
		  <li>Summoner</li>
		  <li>Gifted</li>
	      <li>Paladin</li>
		  <li>TM_Sniper</li>
		  <li>Druid</li>
		  <li>Bladedancer</li>
		  <li>Gladiator</li>
		  <li>Necromancer</li>
		  <li>Priest</li>
		  <li>Ranger</li>
		  <li>Lich</li>
		  <li>TM_Bard</li>
		</conflictingTraits>	
	</TraitDef>

</Defs>